{
    "props": {
        "pageProps": {
            "user": {
                "calendlyLink": null,
                "canProvide": null,
                "currentRole": null,
                "educationExperiences": [],
                "email": "austin@moninger.org",
                "firstName": "Austin",
                "greeting": null,
                "greetingEmoji": null,
                "hqPosition": null,
                "hubCity": null,
                "id": "17",
                "intro": "",
                "isActiveFellow": null,
                "isActiveHq": null,
                "isActiveVp": null,
                "isAlumni": true,
                "lastLoggedIn": "2023-02-26T01:08:46",
                "lastName": "Moninger",
                "linkedinName": "austinmoninger",
                "linkedinUrl": "https://linkedin.com/in/austinmoninger/",
                "location": null,
                "lookingFor": null,
                "meetWithBlurb": null,
                "podId": null,
                "prismUuid": "c9435d82-fab7-497c-936e-b7e1bd97d1bd",
                "profilePicUrl": "https://s3.us-east-2.amazonaws.com/cdn.os.contrary.com/img/profile_pics/17_Austin_Moninger.png",
                "roles": [
                    "Alumni"
                ],
                "secondaryEmail": null,
                "slackUrl": null,
                "twitterHandle": null,
                "twitterUrl": null,
                "workExperiences": []
            },
            "workExperiences": [],
            "educationExperiences": [],
            "userCircles": []
        },
        "__N_SSP": true
    },
    "page": "/dashboard/profile/[id]",
    "query": {
        "id": "17"
    },
    "buildId": "7W34ZBo3EvvtGGmcUwU3r",
    "isFallback": false,
    "gssp": true,
    "scriptLoader": []
}